nicett6/__init__.py
nicett6/buffer.py
nicett6/ciw_helper.py
nicett6/ciw_position_logger.py
nicett6/command_code.py
nicett6/consts.py
nicett6/cover.py
nicett6/cover_manager.py
nicett6/decode.py
nicett6/encode.py
nicett6/image_def.py
nicett6/py.typed
nicett6/serial.py
nicett6/tt6_connection.py
nicett6/tt6_cover.py
nicett6/ttbus_device.py
nicett6/utils.py
nicett6/emulator/__init__.py
nicett6/emulator/__main__.py
nicett6/emulator/config.py
nicett6/emulator/cover_emulator.py
nicett6/emulator/main.py
nicett6/emulator/config/config.json
nicett6/emulator/controller/__init__.py
nicett6/emulator/controller/controller.py
nicett6/emulator/controller/device_manager.py
nicett6/emulator/controller/handle_messages.py
nicett6/emulator/controller/line_handler.py
nicett6/emulator/controller/server_controller.py
nicett6/emulator/controller/web_pos_manager.py
nicett6/emulator/controller/writer_manager.py
nicett6/emulator/controller/writer_wrapper.py
nicett6_pp81381-0.34.dist-info/licenses/LICENSE
nicett6_pp81381-0.34.dist-info/METADATA
nicett6_pp81381-0.34.dist-info/WHEEL
nicett6_pp81381-0.34.dist-info/top_level.txt
nicett6_pp81381-0.34.dist-info/RECORD
