Metadata-Version: 2.4
Name: nicett6-pp81381
Version: 0.34
Summary: Nice TT6 tubular motor controller APIs
Home-page: https://github.com/pp81381/nicett6
Author: Phil Porter
Classifier: Programming Language :: Python :: 3.8
Classifier: Programming Language :: Python :: 3.9
Classifier: Programming Language :: Python :: 3.10
Classifier: Programming Language :: Python :: 3.11
Classifier: License :: OSI Approved :: MIT License
Classifier: Operating System :: OS Independent
Classifier: Topic :: Terminals :: Serial
Classifier: Topic :: Home Automation
Classifier: Framework :: AsyncIO
Classifier: Development Status :: 4 - Beta
Requires-Python: >=3.8
License-File: LICENSE
Requires-Dist: pyserial>=3.4
Requires-Dist: pyserial-asyncio-fast>=0.11
Dynamic: license-file
